<?xml version="1.0" encoding="UTF-8" standalone="yes"?>
<allcases>
    <Case caseNb="25" pid="p25" uid="d24">
        <StartDate>23.11.2014</StartDate>
        <EndDate>28.11.2014</EndDate>
        <Description>Depression</Description>
    </Case>
    <Case caseNb="28" pid="p34" uid="d23">
        <StartDate>20.12.2014</StartDate>
        <EndDate>28.12.2014</EndDate>
        <Description>Depression</Description>
    </Case>
    <Case caseNb="28a" pid="p34" uid="d23">
        <StartDate>01.01.2015</StartDate>
        <EndDate>13.02.2014</EndDate>
        <Description>check Depression</Description>
    </Case>
    <Case caseNb="37" pid="p37" uid="d97">
        <StartDate>14.03.2015</StartDate>
        <EndDate>14.07.2015</EndDate>
        <Description>drug addiction</Description>
    </Case>
</allcases>
