<?xml version="1.0" encoding="UTF-8" standalone="yes"?>
<allPatients>
    <Patient pid="a44">
        <FNname>Rene</FNname>
        <LNname>Meier</LNname>
        <Gender>m</Gender>
        <Address>
            <city>MyCity</city>
            <pcode>3006</pcode>
            <street>MyStreet</street>
        </Address>
        <Birthday>2.10.1952</Birthday>
        <Insurance>Insurance1</Insurance>
    </Patient>
    <Patient pid="m45">
        <FNname>Anna</FNname>
        <LNname>Hofer</LNname>
        <Gender>f</Gender>
        <Address>
            <city>MyCity</city>
            <pcode>3006</pcode>
            <street>MyStreet</street>
        </Address>
        <Birthday>23.04.1976</Birthday>
        <Insurance>Arcosana</Insurance>
    </Patient>
    <Patient pid="a22">
        <FNname>Stephan</FNname>
        <LNname>Wyss</LNname>
        <Gender>m</Gender>
        <Address>
            <city>MyCity</city>
            <pcode>3006</pcode>
            <street>MyStreet</street>
        </Address>
        <Birthday>12.09.1986</Birthday>
        <Insurance>Insurance2</Insurance>
    </Patient>
    <Patient pid="a28">
        <FNname>Gino</FNname>
        <LNname>Wyss</LNname>
        <Gender>m</Gender>
        <Address>
            <city>MyCity</city>
            <pcode>3006</pcode>
            <street>MyStreet</street>
        </Address>
        <Birthday>21.06.1967</Birthday>
        <Insurance>Insurance3</Insurance>
    </Patient>
</allPatients>
